[{"title":"How-To Geek","link":"http:\/\/feeds.howtogeek.com\/howtogeek"},{"title":"TorrentFreak","link":"http:\/\/feeds.feedburner.com\/Torrentfreak"},{"title":"Ars Technica","link":"http:\/\/feeds.arstechnica.com\/arstechnica\/index\/"},{"title":"MakeUseOf","link":"http:\/\/feeds.feedburner.com\/Makeuseof"},{"title":"AddictiveTips","link":"http:\/\/www.addictivetips.com\/feed\/"},{"title":"Android Police","link":"http:\/\/feeds.feedburner.com\/AndroidPolice"},{"title":"GSMArena","link":"http:\/\/www.gsmarena.com\/rss-news-reviews.php3"},{"title":"Lifehacker UK","link":"http:\/\/feeds.feedburner.com\/LifehackerUK-UKPostsOnly"},{"title":"Lifehacker","link":"http:\/\/feeds.gawker.com\/lifehacker\/vip"},{"title":"The Register","link":"http:\/\/www.theregister.co.uk\/headlines.atom"},{"title":"Joel on Software","link":"http:\/\/www.joelonsoftware.com\/rss.xml"},{"title":"A Few Thoughts on Cryptographic Engineering","link":"http:\/\/feeds.feedburner.com\/AFewThoughtsOnCryptographicEngineering"},{"title":"Procedural World","link":"http:\/\/procworld.blogspot.com\/feeds\/posts\/default"},{"title":"gHacks Technology News","link":"http:\/\/www.ghacks.net\/feed\/"},{"title":"One Thing Well","link":"http:\/\/onethingwell.org\/rss"}]